RV32IM.v
module RV32IM(input wire clock, input wire reset_n, output wire [31:0] pc_out, output wire [31:0] op_out, output wire [31:0] alu_out, output wire [8:0] uart_out);
// Copyright (c) 2020 asfdrwe (asfdrwe@gmail.com)
// SPDX-License-Identifier: MIT
  // REGISTER
  reg [31:0] pc;
  assign pc_out = pc; // for DEBUG
  reg [31:0] regs[0:31];

  // MEMORY 64KB 
  reg [7:0] mem[0:16'hffff]; // MEMORY 64KB
  initial $readmemh("test.hex", mem); // MEMORY INITIALIZE 

  // UART OUTPUT and CYCLE COUNTER
  reg [8:0] uart = 9'b0; // uart[8] for output sign, uart[7:0] for data
  assign uart_out = uart;
  localparam [31:0] UART_MMIO_ADDR = 32'h0000_fff0; // ADDRESS 0xfff0 for UART
  reg [31:0] counter = 32'b0;
  localparam [31:0] COUNTER_MMIO_ADDR = 32'h0000_fff4; // ADDRESS 0xfff4 for COUNTER

  // FETCH
  wire [31:0] opcode;
  assign opcode = {mem[pc + 3], mem[pc + 2], mem[pc + 1], mem[pc]}; // little endian
  assign op_out = opcode; // for DEBUG

  // DECODE
  wire [5:0] r_addr1, r_addr2, w_addr;
  wire [31:0] imm;
  wire [4:0] alucon;
  wire [2:0] funct3;
  wire op1sel, op2sel, mem_rw, rf_wen;
  wire [1:0] wb_sel, pc_sel;

  wire [6:0] op;
  assign op = opcode[6:0];

  localparam [6:0] RFORMAT       = 7'b0110011;
  localparam [6:0] IFORMAT_ALU   = 7'b0010011;
  localparam [6:0] IFORMAT_LOAD  = 7'b0000011;
  localparam [6:0] SFORMAT       = 7'b0100011;
  localparam [6:0] SBFORMAT      = 7'b1100011;
  localparam [6:0] UFORMAT_LUI   = 7'b0110111;
  localparam [6:0] UFORMAT_AUIPC = 7'b0010111;
  localparam [6:0] UJFORMAT      = 7'b1101111;
  localparam [6:0] IFORMAT_JALR  = 7'b1100111;
  localparam [6:0] ECALLEBREAK   = 7'b1110011;
  localparam [6:0] FENCE         = 7'b0001111;
  localparam [6:0] MULDIV        = 7'b0110011;

  assign r_addr1 = (op == UFORMAT_LUI) ? 5'b0 : opcode[19:15];
  assign r_addr2 = opcode[24:20];
  assign w_addr =  opcode[11:7];

  wire [31:0] i_sext, s_sext, sb_sext, u_sext, uj_sext;

  assign i_sext = ((op == IFORMAT_ALU) && ((opcode[14:12] == 3'b001) || (opcode[14:12] == 3'b101))) ? {27'b0, opcode[24:20]} :  // SLLI or SRLI or SRAI
                                                                           (opcode[31] == 1'b1) ? {20'hfffff, opcode[31:20]} : {20'h00000, opcode[31:20]};
  assign s_sext = (opcode[31] == 1'b1) ? {20'hfffff, opcode[31:25],opcode[11:7]} : {20'h00000, opcode[31:25],opcode[11:7]};
  assign sb_sext = (opcode[31] == 1'b1) ? {19'h7ffff, opcode[31], opcode[7], opcode[30:25], opcode[11:8], 1'b0} : {19'h00000, opcode[31], opcode[7], opcode[30:25], opcode[11:8], 1'b0};
  assign u_sext = {opcode[31:12], 12'b0};
  assign uj_sext = (opcode[31] == 1'b1) ? {11'h7ff, opcode[31], opcode[19:12], opcode[20], opcode[30:21], 1'b0} : {11'h000, opcode[31], opcode[19:12], opcode[20], opcode[30:21], 1'b0};
  assign imm = ((op == IFORMAT_ALU) || (op == IFORMAT_LOAD) || (op == IFORMAT_JALR))  ? i_sext :
                (op == SFORMAT)        ? s_sext :
                (op == SBFORMAT)       ? sb_sext :
               ((op == UFORMAT_LUI) || (op == UFORMAT_AUIPC)) ? u_sext :
                (op == UJFORMAT)       ? uj_sext : 32'b0;
  assign alucon = ((op == RFORMAT) || (op == MULDIV)) ? {opcode[30], opcode[25], opcode[14:12]} :
                  (op == IFORMAT_ALU) ? ((opcode[14:12] == 3'b101) ? {opcode[30], opcode[25], opcode[14:12]} : // SRLI or SRAI
                                        {2'b00, opcode[14:12]}) : 5'b0;
  assign funct3 = opcode[14:12];
  assign op1sel = ((op == SBFORMAT) || (op == UFORMAT_AUIPC) || (op == UJFORMAT)) ? 1'b1 : 1'b0;
  assign op2sel = ((op == RFORMAT) || (op == MULDIV)) ? 1'b0 : 1'b1;
  assign mem_rw = (op == SFORMAT) ? 1'b1 : 1'b0;
  assign wb_sel = (op == IFORMAT_LOAD) ? 2'b01 :
                  ((op == UJFORMAT) || (op == IFORMAT_JALR)) ? 2'b10 : 2'b00;
  assign rf_wen = (((op == RFORMAT) && ({opcode[31],opcode[29:25]} == 6'b000000)) ||
                   ((op == MULDIV) && ({opcode[31:25]} == 7'b000001)) ||
                   ((op == IFORMAT_ALU) && (({opcode[31:25], opcode[14:12]} == 10'b00000_00_001) || ({opcode[31], opcode[29:25], opcode[14:12]} == 9'b0_000_00_101) ||  // SLLI or SRLI or SRAI
                                            (opcode[14:12] == 3'b000) || (opcode[14:12] == 3'b010) || (opcode[14:12] == 3'b011) || (opcode[14:12] == 3'b100) || (opcode[14:12] == 3'b110) || (opcode[14:12] == 3'b111))) ||
                   (op == IFORMAT_LOAD) || (op == UFORMAT_LUI) || (op == UFORMAT_AUIPC) || (op == UJFORMAT) || (op == IFORMAT_JALR)) ? 1'b1 : 1'b0;
  assign pc_sel = (op == SBFORMAT) ? 2'b01 :
                  ((op == UJFORMAT) || (op == IFORMAT_JALR) || (op == ECALLEBREAK)) ? 2'b10 : 2'b00;

  // EXECUTION

  // REGISTER READ                  
  wire [31:0] r_data1, r_data2;
  assign r_data1 = (r_addr1 == 5'b00000) ? 32'b0 : regs[r_addr1]; 
  assign r_data2 = (r_addr2 == 5'b00000) ? 32'b0 : regs[r_addr2]; 

  // SELECTOR  
  wire [31:0] s_data1, s_data2;
  assign s_data1 = (op1sel == 1'b1) ? pc : r_data1;
  assign s_data2 = (op2sel == 1'b1) ? imm : r_data2;

  // ALU
  wire [31:0] alu_data;
  reg [63:0] tmpalu;

  function [31:0] ALU_EXEC( input [4:0] control, input [31:0] data1, input [31:0] data2);
    case(control)
    5'b00000: // ADD ADDI (ADD)
      ALU_EXEC = data1 + data2;
    5'b10000: // SUB (SUB)
      ALU_EXEC = data1 - data2;
    5'b00001: // SLL SLLI (SHIFT LEFT (LOGICAL))
      ALU_EXEC = data1 << data2[4:0];
    5'b00010: // SLT SLTI (SET_ON_LESS_THAN (SIGNED))
      ALU_EXEC = ($signed(data1) < $signed(data2)) ? 32'b1 :32'b0;
    5'b00011: // SLTU SLTUI (SET_ON_LESS_THAN (UNSIGNED))
      ALU_EXEC = (data1 < data2) ? 32'b1 :32'b0;
    5'b00100: // XOR XORI (XOR)
      ALU_EXEC = data1 ^ data2;
    5'b00101: // SRL SRLI (SHIFT RIGHT (LOGICAL))
      ALU_EXEC = data1 >> data2[4:0];
    5'b10101: // SRA SRAI (SHIFT RIGHT (ARITHMETIC))
      ALU_EXEC = $signed(data1[31:0]) >>> data2[4:0];
    5'b00110: // OR ORI (OR)
      ALU_EXEC = data1 | data2;
    5'b00111: // AND ANDI (AND)
      ALU_EXEC = data1 & data2;
    5'b01000: // MUL (MULTIPLE)
      ALU_EXEC = data1 * data2;
    5'b01001: begin // MULH (MULTIPLE)
      tmpalu = $signed(data1) * $signed(data2);
      ALU_EXEC = $signed(tmpalu) >>> 32;
    end
    5'b01010: begin // MULHSU (MULTIPLE)
      tmpalu = $signed(data1) * $signed({1'b0, data2});
      ALU_EXEC = tmpalu >> 32;
    end
    5'b01011: begin // MULHU (MULTIPLE)
      tmpalu = data1 * data2;
      ALU_EXEC = tmpalu >> 32;
    end
    5'b01100: // DIV (DIVIDE)
      ALU_EXEC = (data2 == 32'b0) ? 32'hffff_ffff : 
                 ((data1 == 32'h8000_0000) && (data2 == 32'hffff_ffff)) ? 32'h8000_0000 : $signed($signed(data1) / $signed(data2));
    5'b01101: // DIVU (DIVIDE)
      ALU_EXEC = (data2 == 32'b0) ? 32'hffff_ffff : (data1 / data2);
    5'b01110: // REM (DIVIDE REMINDER)
      ALU_EXEC = (data2 == 32'b0) ? data1 : 
                 ((data1 == 32'h8000_0000) && (data2 == 32'hffff_ffff)) ? 32'h0 : $signed($signed(data1) % $signed(data2));
    5'b01111: // REMU (DIVIDE REMINDER)
      ALU_EXEC = (data2 == 32'b0) ? data1 : (data1 % data2);
    default: // ILLEGAL
      ALU_EXEC = 32'b0;
    endcase
  endfunction

  assign alu_data = ALU_EXEC(alucon, s_data1, s_data2);
  assign alu_out = alu_data; // for DEBUG

  // BRANCH
  wire pc_sel2;

  function BRANCH_EXEC( input [2:0] branch_op, input [31:0] data1, input [31:0] data2, input [1:0] pc_sel);
    case(pc_sel)
    2'b00: // PC + 4
      BRANCH_EXEC = 1'b0;
    2'b01: begin // BRANCH
      case(branch_op)
      3'b000: // BEQ
        BRANCH_EXEC = (data1 == data2) ? 1'b1 : 1'b0;
      3'b001: // BNE
        BRANCH_EXEC = (data1 != data2) ? 1'b1 : 1'b0;
      3'b100: begin // BLT
        BRANCH_EXEC = ($signed(data1) < $signed(data2)) ? 1'b1 : 1'b0;
      end
      3'b101: begin // BGE
        BRANCH_EXEC = ($signed(data1) >= $signed(data2)) ? 1'b1 : 1'b0;
      end
      3'b110: // BLTU
        BRANCH_EXEC = (data1 < data2) ? 1'b1 : 1'b0;
      3'b111: // BGEU
        BRANCH_EXEC = (data1 >= data2) ? 1'b1 : 1'b0;
      default: // ILLEGAL
        BRANCH_EXEC = 1'b0;
      endcase
    end 
    2'b10: // JAL JALR
      BRANCH_EXEC = 1'b1;
    default: // ILLEGAL
      BRANCH_EXEC = 1'b0;
    endcase
  endfunction

  assign pc_sel2 = BRANCH_EXEC(funct3, r_data1, r_data2, pc_sel);

  // MEMORY 
  wire [2:0] mem_val;
  wire [31:0] mem_data;
  wire [31:0] mem_addr;
  assign mem_val = funct3;
  assign mem_addr = alu_data;
  
  // MEMORY READ
  assign mem_data = (mem_rw == 1'b1) ? 32'b0 : // when MEMORY WRITE, the output from MEMORY is 32'b0
		    ((mem_val == 3'b010) && (mem_addr == COUNTER_MMIO_ADDR)) ? counter : // MEMORY MAPPED IO for CLOCK CYCLE COUNTER
                     (mem_val == 3'b000) ?  (mem[mem_addr][7] == 1'b1 ? {24'hffffff, mem[mem_addr]} : {24'h000000, mem[mem_addr]}) : // LB
                     (mem_val == 3'b001) ?  (mem[mem_addr + 1][7] == 1'b1 ? {16'hffff, mem[mem_addr + 1], mem[mem_addr]} : {16'h0000, mem[mem_addr + 1], mem[mem_addr]}) : // LH
                     (mem_val == 3'b010) ? {mem[mem_addr + 3], mem[mem_addr + 2], mem[mem_addr + 1], mem[mem_addr]} : // LW
                     (mem_val == 3'b100) ? {24'h000000, mem[mem_addr]} : // LBU
                     (mem_val == 3'b101) ? {16'h0000, mem[mem_addr + 1], mem[mem_addr]} : // LHU
                                           32'b0;
  // MEMORY WRITE
  always @(posedge clock) begin
    if (mem_rw == 1'b1) begin
      case (mem_val)
        3'b000: // SB
          mem[mem_addr] <= #1 r_data2[7:0];
        3'b001: // SH
          {mem[mem_addr + 1], mem[mem_addr]} <= #1 r_data2[15:0];
        3'b010: // SW
          {mem[mem_addr + 3], mem[mem_addr + 2], mem[mem_addr + 1], mem[mem_addr]} <= #1 r_data2;
        default: begin end // ILLEGAL
      endcase
    end
    // MEMORY MAPPED IO to UART
    if ((mem_rw == 1'b1) && (mem_addr == UART_MMIO_ADDR)) begin
      uart <= #1 {1'b1, r_data2[7:0]};
    end else begin
      uart <= #1 9'b0;
    end
  end

  // REGISTER WRITE BACK
  wire [31:0] w_data;
  assign w_data = (wb_sel == 2'b00) ? alu_data : 
                  (wb_sel == 2'b01) ? mem_data :
                  (wb_sel == 2'b10) ? pc + 4 : 32'b0; // ILLEGAL
  always @(posedge clock) begin
    if ((rf_wen == 1'b1) && (w_addr != 5'b00000))
      regs[w_addr] <= #1 w_data;
  end

  // NEXT PC
  wire [31:0] next_pc;
  assign next_pc = (pc_sel2 == 1'b1) ? {alu_data[31:1], 1'b0} : pc + 4;

  // NEXT PC WRITE BACK and CYCLE COUNTER
  always @(posedge clock or negedge reset_n) begin
   if (!reset_n) begin
      pc <= 32'b0;
      counter <= 32'b0;
    end else begin
      pc <= #1 next_pc; 
      counter <= counter + 1;
    end
  end
endmodule

RV32IM_coremark_test.v
module UART(input wire f, input wire [7:0] data);
  always @(*) begin
    if (f == 1'b1) begin
      $write("%c", data);
    end
  end
endmodule 

module RV32IM_test;
  reg clock = 1'b0;
  reg reset_n = 1'b0;
  wire [31:0] pc_out, op_out, alu_out;
  wire [8:0] uart_out;
  
  UART u1(uart_out[8], uart_out[7:0]);
  RV32IM rv1(clock, reset_n, pc_out, op_out, alu_out, uart_out);

  initial begin
    clock = 1'b0;
    forever begin
      #1 clock = ~clock;
    end
  end

  initial begin
    reset_n = 1'b0;

    #1 reset_n = 1'b1;
    #10000000 $finish;
  end

endmodule

RV32IM.vcd
$date
	Sat Nov 21 19:09:35 2020
$end
$version
	Icarus Verilog
$end
$timescale
	1s
$end
$scope module RV32IM_test $end
$var wire 9 ! uart_out [8:0] $end
$var wire 32 " pc_out [31:0] $end
$var wire 32 # op_out [31:0] $end
$var wire 32 $ alu_out [31:0] $end
$var reg 1 % clock $end
$var reg 1 & reset_n $end
$scope module rv1 $end
$var wire 32 ' alu_out [31:0] $end
$var wire 1 % clock $end
$var wire 32 ( mem_addr [31:0] $end
$var wire 3 ) mem_val [2:0] $end
$var wire 32 * op_out [31:0] $end
$var wire 32 + pc_out [31:0] $end
$var wire 1 & reset_n $end
$var wire 9 , uart_out [8:0] $end
$var wire 2 - wb_sel [1:0] $end
$var wire 32 . w_data [31:0] $end
$var wire 6 / w_addr [5:0] $end
$var wire 32 0 uj_sext [31:0] $end
$var wire 32 1 u_sext [31:0] $end
$var wire 32 2 sb_sext [31:0] $end
$var wire 32 3 s_sext [31:0] $end
$var wire 32 4 s_data2 [31:0] $end
$var wire 32 5 s_data1 [31:0] $end
$var wire 1 6 rf_wen $end
$var wire 32 7 r_data2 [31:0] $end
$var wire 32 8 r_data1 [31:0] $end
$var wire 6 9 r_addr2 [5:0] $end
$var wire 6 : r_addr1 [5:0] $end
$var wire 1 ; pc_sel2 $end
$var wire 2 < pc_sel [1:0] $end
$var wire 32 = opcode [31:0] $end
$var wire 1 > op2sel $end
$var wire 1 ? op1sel $end
$var wire 7 @ op [6:0] $end
$var wire 32 A next_pc [31:0] $end
$var wire 1 B mem_rw $end
$var wire 32 C mem_data [31:0] $end
$var wire 32 D imm [31:0] $end
$var wire 32 E i_sext [31:0] $end
$var wire 3 F funct3 [2:0] $end
$var wire 5 G alucon [4:0] $end
$var wire 32 H alu_data [31:0] $end
$var reg 32 I counter [31:0] $end
$var reg 32 J pc [31:0] $end
$var reg 64 K tmpalu [63:0] $end
$var reg 9 L uart [8:0] $end
$scope function ALU_EXEC $end
$var reg 32 M ALU_EXEC [31:0] $end
$var reg 5 N control [4:0] $end
$var reg 32 O data1 [31:0] $end
$var reg 32 P data2 [31:0] $end
$upscope $end
$scope function BRANCH_EXEC $end
$var reg 1 Q BRANCH_EXEC $end
$var reg 3 R branch_op [2:0] $end
$var reg 32 S data1 [31:0] $end
$var reg 32 T data2 [31:0] $end
$var reg 2 U pc_sel [1:0] $end
$upscope $end
$upscope $end
$upscope $end
$enddefinitions $end
#0
$dumpvars
b0 U
bx T
b0 S
b0 R
0Q
b10100 P
b0 O
b0 N
b10100 M
b0 L
bx K
b0 J
b0 I
b10100 H
b0 G
b0 F
b10100 E
b10100 D
b1100011 C
0B
b100 A
b10011 @
0?
1>
b1010000000000000010010011 =
b0 <
0;
b0 :
b10100 9
b0 8
bx 7
16
b0 5
b10100 4
b1 3
b100000000000 2
b1010000000000000000000000 1
b10100 0
b1 /
b10100 .
b0 -
b0 ,
b0 +
b1010000000000000010010011 *
b0 )
b10100 (
b10100 '
0&
0%
b10100 $
b1010000000000000010010011 #
b0 "
b0 !
$end
#1
b1 I
1&
1%
#2
b1100000 C
b110 .
b110 (
b110 $
b110 '
b110 H
b110 M
b110 P
b110 4
b110 D
b110 E
b110 0
b10 3
b10 2
b110 9
b11000000000000000000000 1
b10 /
b1000 A
b11000000000000100010011 #
b11000000000000100010011 *
b11000000000000100010011 =
b100 "
b100 +
b100 J
0%
#3
b10 I
1%
#4
16
b10100 O
b10 .
b10100 5
b0 C
b0 D
b10 (
b10 $
b10 '
b10 H
b10 M
b1111 N
b110 T
b10100 S
b100010 E
b10100 8
b1111 G
0>
b110 7
b1 :
b101110 3
b101110 2
b1111000000100010 0
b111 R
b10 9
b1110 /
b10001000001111000000000000 1
b111 )
b111 F
b110011 @
b1100 A
b10001000001111011100110011 #
b10001000001111011100110011 *
b10001000001111011100110011 =
b1000 "
b1000 +
b1000 J
0%
#5
b11 I
1%
#6
16
b10 P
b0 O
b10 4
b0 5
b0 S
b10 .
b1000000 C
b10 D
b10 E
b0 8
b10 (
b10 $
b10 '
b10 H
b10 M
b0 N
1>
b0 :
b10 0
b0 G
b0 R
b111 3
b100000000110 2
b1000000000000000000000 1
b0 )
b0 F
b10011 @
b111 /
b10000 A
b1000000000001110010011 #
b1000000000001110010011 *
b1000000000001110010011 =
b1100 "
b1100 +
b1100 J
0%
#7
b100 I
1%
#8
b11 3
b100000000010 2
b11 /
b10100 A
b1000000000000110010011 #
b1000000000000110010011 *
b1000000000000110010011 =
b10000 "
b10000 +
b10000 J
0%
#9
b101 I
1%
#10
06
b11011100 .
b11011100 (
b11011100 $
b11011100 '
b11011100 H
b11011100 M
b11001000 P
b10100 O
b11001000 4
b10100 5
b10 S
b1111 C
b11001000 D
1?
b10 8
b10 T
b11000111 E
b1110 :
b10 7
b1110001100011000110 0
0;
0Q
b1 U
b1 R
b1 <
b11001000 3
b11001000 2
b111 9
b1100011101110001000000000000 1
b1 )
b1 F
b1100011 @
b1000 /
b11000 A
b1100011101110001010001100011 #
b1100011101110001010001100011 *
b1100011101110001010001100011 =
b10100 "
b10100 +
b10100 J
0%
#11
b110 I
1%
#12
16
bx C
b11111111111111111111111111101100 P
b11111111111111111111111111101100 4
b0 S
b11111111111111111111111111101100 D
b0 N
0?
b0 8
bx T
b11111111111111111111111111101100 E
b0 G
b11111111111111111111111111101100 .
b0 :
bx 7
b11111111111100000000011111101100 0
b0 U
b0 R
b0 <
b11111111111111111111111111100001 3
b11111111111111111111111111100000 2
b11111111111111111111111111101100 (
b11111111111111111111111111101100 $
b11111111111111111111111111101100 '
b11111111111111111111111111101100 H
b11111111111111111111111111101100 M
b0 O
b1100 9
b11111110110000000000000000000000 1
b0 )
b0 F
b10011 @
b1 /
b0 5
b11100 A
b11111110110000000000000010010011 #
b11111110110000000000000010010011 *
b11111110110000000000000010010011 =
b11000 "
b11000 +
b11000 J
0%
#13
b111 I
1%
#14
b1100000 C
b110 .
b110 (
b110 $
b110 '
b110 H
b110 M
b110 P
b110 4
b110 D
b110 E
b110 0
b10 3
b10 2
b110 9
b11000000000000000000000 1
b10 /
b100000 A
b11000000000000100010011 #
b11000000000000100010011 *
b11000000000000100010011 =
b11100 "
b11100 +
b11100 J
0%
#15
b1000 I
1%
#16
16
b11111111111111111111111111101100 O
b10 .
b11111111111111111111111111101100 5
b0 C
b0 D
b10 (
b10 $
b10 '
b10 H
b10 M
b1111 N
b110 T
b11111111111111111111111111101100 S
b100010 E
b11111111111111111111111111101100 8
b1111 G
0>
b110 7
b1 :
b101110 3
b101110 2
b1111000000100010 0
b111 R
b10 9
b1110 /
b10001000001111000000000000 1
b111 )
b111 F
b110011 @
b100100 A
b10001000001111011100110011 #
b10001000001111011100110011 *
b10001000001111011100110011 =
b100000 "
b100000 +
b100000 J
0%
#17
b1001 I
1%
#18
16
b10 P
b0 O
b10 4
b0 5
b0 S
b10 .
b1000000 C
b10 D
b10 E
b0 8
b10 (
b10 $
b10 '
b10 H
b10 M
b0 N
1>
b0 :
b10 0
b0 G
b0 R
b111 3
b100000000110 2
b1000000000000000000000 1
b0 )
b0 F
b10011 @
b111 /
b101000 A
b1000000000001110010011 #
b1000000000001110010011 *
b1000000000001110010011 =
b100100 "
b100100 +
b100100 J
0%
#19
b1010 I
1%
#20
b1 C
b11 .
b11 (
b11 $
b11 '
b11 H
b11 M
b11 P
b11 4
b11 D
b10 T
b11 E
b10 7
b100000000010 0
b11 3
b100000000010 2
b11 9
b1100000000000000000000 1
b11 /
b101100 A
b1100000000000110010011 #
b1100000000000110010011 *
b1100000000000110010011 =
b101000 "
b101000 +
b101000 J
0%
#21
b1011 I
1%
#22
06
b11011100 .
b11011100 (
b11011100 $
b11011100 '
b11011100 H
b11011100 M
b10110000 P
b101100 O
b10110000 4
b101100 5
b10 S
b1111 C
b10110000 D
1?
b10 8
b10100111 E
0;
0Q
b1 U
b1110 :
b1110001100010100110 0
b1 <
b10110000 3
b10110000 2
b10 T
b1 R
b111 9
b1010011101110001000000000000 1
b1 )
b1 F
b1100011 @
b10000 /
b110000 A
b10 7
b1010011101110001100001100011 #
b1010011101110001100001100011 *
b1010011101110001100001100011 =
b101100 "
b101100 +
b101100 J
0%
#23
b1100 I
1%
#24
16
b1100011 C
b10100 P
b10100 4
b0 S
b10100 D
b0 N
0?
b0 8
bx T
b10100 E
b0 G
b10100 .
b0 :
bx 7
b10100 0
b0 U
b0 R
b0 <
b1 3
b100000000000 2
b10100 (
b10100 $
b10100 '
b10100 H
b10100 M
b0 O
b10100 9
b1010000000000000000000000 1
b0 )
b0 F
b10011 @
b1 /
b0 5
b110100 A
b1010000000000000010010011 #
b1010000000000000010010011 *
b1010000000000000010010011 =
b110000 "
b110000 +
b110000 J
0%
#25
b1101 I
1%
#26
bx C
b11111111111111111111111111111010 .
b11111111111111111111111111111010 (
b11111111111111111111111111111010 $
b11111111111111111111111111111010 '
b11111111111111111111111111111010 H
b11111111111111111111111111111010 M
b11111111111111111111111111111010 P
b11111111111111111111111111111010 4
b11111111111111111111111111111010 D
b11111111111111111111111111111010 E
b11111111111100000000011111111010 0
b11111111111111111111111111100010 3
b11111111111111111111011111100010 2
b11010 9
b11111111101000000000000000000000 1
b10 /
b111000 A
b11111111101000000000000100010011 #
b11111111101000000000000100010011 *
b11111111101000000000000100010011 =
b110100 "
b110100 +
b110100 J
0%
#27
b1110 I
1%
#28
16
b10100 O
b10100 .
b10100 5
b0 C
b0 D
b10100 (
b10100 $
b10100 '
b10100 H
b10100 M
b1111 N
b11111111111111111111111111111010 T
b10100 S
b100010 E
b10100 8
b1111 G
0>
b11111111111111111111111111111010 7
b1 :
b101110 3
b101110 2
b1111000000100010 0
b111 R
b10 9
b1110 /
b10001000001111000000000000 1
b111 )
b111 F
b110011 @
b111100 A
b10001000001111011100110011 #
b10001000001111011100110011 *
b10001000001111011100110011 =
b111000 "
b111000 +
b111000 J
0%
#29
b1111 I
1%
#30
16
b10100 P
b0 O
b0 5
b10100 .
b1100011 C
b10100 D
b10100 4
bx T
b0 S
b10100 E
b0 8
b10100 (
b10100 $
b10100 '
b10100 H
b10100 M
b0 N
1>
bx 7
b0 :
b10100 0
b0 G
b0 R
b111 3
b100000000110 2
b10100 9
b1010000000000000000000000 1
b0 )
b0 F
b10011 @
b111 /
b1000000 A
b1010000000000001110010011 #
b1010000000000001110010011 *
b1010000000000001110010011 =
b111100 "
b111100 +
b111100 J
0%
#31
b10000 I
1%
#32
b10011 C
b100 .
b100 (
b100 $
b100 '
b100 H
b100 M
b100 P
b100 4
b100 D
b100 E
b100 0
b11 3
b100000000010 2
b100 9
b10000000000000000000000 1
b11 /
b1000100 A
b10000000000000110010011 #
b10000000000000110010011 *
b10000000000000110010011 =
b1000000 "
b1000000 +
b1000000 J
0%
#33
b10001 I
1%
#34
06
b11011100 .
b11011100 (
b11011100 $
b11011100 '
b11011100 H
b11011100 M
b10011000 P
b1000100 O
b10011000 4
b1000100 5
b10100 S
b1111 C
b10011000 D
1?
b10100 8
b10100 T
b10000111 E
b1110 :
b10100 7
b1110001100010000110 0
0;
0Q
b1 U
b1 R
b1 <
b10011000 3
b10011000 2
b111 9
b1000011101110001000000000000 1
b1 )
b1 F
b1100011 @
b11000 /
b1001000 A
b1000011101110001110001100011 #
b1000011101110001110001100011 *
b1000011101110001110001100011 =
b1000100 "
b1000100 +
b1000100 J
0%
#35
b10010 I
1%
#36
16
bx C
b11111111111111111111111111101100 P
b11111111111111111111111111101100 4
b0 S
b11111111111111111111111111101100 D
b0 N
0?
b0 8
bx T
b11111111111111111111111111101100 E
b0 G
b11111111111111111111111111101100 .
b0 :
bx 7
b11111111111100000000011111101100 0
b0 U
b0 R
b0 <
b11111111111111111111111111100001 3
b11111111111111111111111111100000 2
b11111111111111111111111111101100 (
b11111111111111111111111111101100 $
b11111111111111111111111111101100 '
b11111111111111111111111111101100 H
b11111111111111111111111111101100 M
b0 O
b1100 9
b11111110110000000000000000000000 1
b0 )
b0 F
b10011 @
b1 /
b0 5
b1001100 A
b11111110110000000000000010010011 #
b11111110110000000000000010010011 *
b11111110110000000000000010010011 =
b1001000 "
b1001000 +
b1001000 J
0%
#37
b10011 I
1%
#38
b11111111111111111111111111111010 .
b11111111111111111111111111111010 (
b11111111111111111111111111111010 $
b11111111111111111111111111111010 '
b11111111111111111111111111111010 H
b11111111111111111111111111111010 M
b11111111111111111111111111111010 P
b11111111111111111111111111111010 4
b11111111111111111111111111111010 D
b11111111111111111111111111111010 E
b11111111111100000000011111111010 0
b11111111111111111111111111100010 3
b11111111111111111111011111100010 2
b11010 9
b11111111101000000000000000000000 1
b10 /
b1010000 A
b11111111101000000000000100010011 #
b11111111101000000000000100010011 *
b11111111101000000000000100010011 =
b1001100 "
b1001100 +
b1001100 J
0%
#39
b10100 I
1%
#40
16
b11111111111111111111111111101100 O
b11111111111111111111111111101100 .
b11111111111111111111111111101100 5
b0 C
b0 D
b11111111111111111111111111101100 (
b11111111111111111111111111101100 $
b11111111111111111111111111101100 '
b11111111111111111111111111101100 H
b11111111111111111111111111101100 M
b1111 N
b11111111111111111111111111111010 T
b11111111111111111111111111101100 S
b100010 E
b11111111111111111111111111101100 8
b1111 G
0>
b11111111111111111111111111111010 7
b1 :
b101110 3
b101110 2
b1111000000100010 0
b111 R
b10 9
b1110 /
b10001000001111000000000000 1
b111 )
b111 F
b110011 @
b1010100 A
b10001000001111011100110011 #
b10001000001111011100110011 *
b10001000001111011100110011 =
b1010000 "
b1010000 +
b1010000 J
0%
#41
b10101 I
1%
#42
16
b11111111111111111111111111101100 P
b0 O
b0 5
b11111111111111111111111111101100 .
bx C
b11111111111111111111111111101100 D
b11111111111111111111111111101100 4
bx T
b0 S
b11111111111111111111111111101100 E
b0 8
b11111111111111111111111111101100 (
b11111111111111111111111111101100 $
b11111111111111111111111111101100 '
b11111111111111111111111111101100 H
b11111111111111111111111111101100 M
b0 N
1>
bx 7
b0 :
b11111111111100000000011111101100 0
b0 G
b0 R
b11111111111111111111111111100111 3
b11111111111111111111111111100110 2
b1100 9
b11111110110000000000000000000000 1
b0 )
b0 F
b10011 @
b111 /
b1011000 A
b11111110110000000000001110010011 #
b11111110110000000000001110010011 *
b11111110110000000000001110010011 =
b1010100 "
b1010100 +
b1010100 J
0%
#43
b10110 I
1%
#44
b1 C
b101 .
b101 (
b101 $
b101 '
b101 H
b101 M
b101 P
b101 4
b101 D
b101 E
b100000000100 0
b11 3
b100000000010 2
b101 9
b10100000000000000000000 1
b11 /
b1011100 A
b10100000000000110010011 #
b10100000000000110010011 *
b10100000000000110010011 =
b1011000 "
b1011000 +
b1011000 J
0%
#45
b10111 I
1%
#46
06
b11011100 .
b11011100 (
b11011100 $
b11011100 '
b11011100 H
b11011100 M
b10000000 P
b1011100 O
b10000000 4
b1011100 5
b11111111111111111111111111101100 S
b1111 C
b10000000 D
1?
b11111111111111111111111111101100 8
b11111111111111111111111111101100 T
b10000111 E
b1110 :
b11111111111111111111111111101100 7
b1110001100010000110 0
0;
0Q
b1 U
b1 R
b1 <
b10000000 3
b10000000 2
b111 9
b1000011101110001000000000000 1
b1 )
b1 F
b1100011 @
b0 /
b1100000 A
b1000011101110001000001100011 #
b1000011101110001000001100011 *
b1000011101110001000001100011 =
b1011100 "
b1011100 +
b1011100 J
0%
#47
b11000 I
1%
#48
b10000000000000000000000000000000 P
16
bx C
b10000000000000000000000000000000 4
b10000000000000000000000000000000 D
0?
b0 T
b0 S
b11111111111111111111100000000000 E
b0 8
b10000000000000000000000000000000 .
b0 7
b11111111111100000000000000000000 0
b0 U
b0 R
b0 :
b0 <
b11111111111111111111100000000001 3
b11111111111111111111100000000000 2
b10000000000000000000000000000000 (
b10000000000000000000000000000000 $
b10000000000000000000000000000000 '
b10000000000000000000000000000000 H
b10000000000000000000000000000000 M
b0 O
b0 9
b10000000000000000000000000000000 1
b0 )
b0 F
b110111 @
b1 /
b0 5
b1100100 A
b10000000000000000000000010110111 #
b10000000000000000000000010110111 *
b10000000000000000000000010110111 =
b1100000 "
b1100000 +
b1100000 J
0%
#49
b11001 I
1%
#50
b0 C
b1 .
b1 (
b1 $
b1 '
b1 H
b1 M
b1 P
16
b1 4
b1 D
b10000000000000000000000000000000 T
b1 E
b10000000000000000000000000000000 7
b100000000000 0
b10 3
b10 2
b1 9
b100000000000000000000 1
b10011 @
b10 /
b1101000 A
b100000000000100010011 #
b100000000000100010011 *
b100000000000100010011 =
b1100100 "
b1100100 +
b1100100 J
0%
#51
b11010 I
1%
